whyus/__init__.py
whyus/admin.py
whyus/apps.py
whyus/static/css/whyus/bethany_ds.css
whyus/static/css/whyus/medicio_ds.css
whyus/static/css/whyus/medilab_ds.css
whyus/static/css/whyus/mentor_ds.css
whyus/templates/whyus/_common.html
whyus/templates/whyus/bethany_ds.html
whyus/templates/whyus/medicio_ds.html
whyus/templates/whyus/medilab_ds.html
whyus/templates/whyus/mentor_ds.html
whyus/templatetags/__init__.py
whyus/templatetags/whyus_tags.py
django_whyus_ds-0.1.1.dist-info/LICENSE
django_whyus_ds-0.1.1.dist-info/METADATA
django_whyus_ds-0.1.1.dist-info/WHEEL
django_whyus_ds-0.1.1.dist-info/top_level.txt
django_whyus_ds-0.1.1.dist-info/RECORD
